kettle_provider/__init__.py
kettle_provider/hooks/__init__.py
kettle_provider/operators/__init__.py
kettle_provider/operators/kettle_operator.py
kettle_provider/sensors/__init__.py
apache_airflow_providers_kettle-1.0.7.dist-info/LICENSE
apache_airflow_providers_kettle-1.0.7.dist-info/METADATA
apache_airflow_providers_kettle-1.0.7.dist-info/WHEEL
apache_airflow_providers_kettle-1.0.7.dist-info/entry_points.txt
apache_airflow_providers_kettle-1.0.7.dist-info/top_level.txt
apache_airflow_providers_kettle-1.0.7.dist-info/RECORD
